Workbook

Sheet Dashboard
B2: Personal Finance Tracker
B4: Figures in USD | C4: January | D4: February | E4: March | F4: April | G4: May | H4: June | I4: July | J4: August | K4: September | L4: October | M4: November | N4: December | P4: YTD Total
B5: Income:
B6: Base Salary | C6: =SUMIFS(Input!$F:$F,Input!$C:$C,Dashboard!C$4,Input!$D:$D,Dashboard!$B6) -> 3500 | D6: =SUMIFS(Input!$F:$F,Input!$C:$C,Dashboard!D$4,Input!$D:$D,Dashboard!$B6) -> 3500 | E6: =SUMIFS(Input!$F:$F,Input!$C:$C,Dashboard!E$4,Input!$D:$D,Dashboard!$B6) -> 3500 | F6: =SUMIFS(Input!$F:$F,Input!$C:$C,Dashboard!F$4,Input!$D:$D,Dashboard!$B6) -> 3500 | G6: =SUMIFS(Input!$F:$F,Input!$C:$C,Dashboard!G$4,Input!$D:$D,Dashboard!$B6) -> 3500 | H6: =SUMIFS(Input!$F:$F,Input!$C:$C,Dashboard!H$4,Input!$D:$D,Dashboard!$B6) -> 3500 | I6: =SUMIFS(Input!$F:$F,Input!$C:$C,Dashboard!I$4,Input!$D:$D,Dashboard!$B6) -> 3500 | J6: =SUMIFS(Input!$F:$F,Input!$C:$C,Dashboard!J$4,Input!$D:$D,Dashboard!$B6) -> 3500 | ... N6: =SUMIFS(Input!$F:$F,Input!$C:$C,Dashboard!N$4,Input!$D:$D,Dashboard!$B6) -> 0 | P6: =SUM(C6:N6) -> 28000
B7: Bonus | C7: =SUMIFS(Input!$F:$F,Input!$C:$C,Dashboard!C$4,Input!$D:$D,Dashboard!$B7) -> 850 | D7: =SUMIFS(Input!$F:$F,Input!$C:$C,Dashboard!D$4,Input!$D:$D,Dashboard!$B7) -> 1025 | E7: =SUMIFS(Input!$F:$F,Input!$C:$C,Dashboard!E$4,Input!$D:$D,Dashboard!$B7) -> 999 | F7: =SUMIFS(Input!$F:$F,Input!$C:$C,Dashboard!F$4,Input!$D:$D,Dashboard!$B7) -> 1243 | G7: =SUMIFS(Input!$F:$F,Input!$C:$C,Dashboard!G$4,Input!$D:$D,Dashboard!$B7) -> 1450 | H7: =SUMIFS(Input!$F:$F,Input!$C:$C,Dashboard!H$4,Input!$D:$D,Dashboard!$B7) -> 2232 | I7: =SUMIFS(Input!$F:$F,Input!$C:$C,Dashboard!I$4,Input!$D:$D,Dashboard!$B7) -> 2231 | J7: =SUMIFS(Input!$F:$F,Input!$C:$C,Dashboard!J$4,Input!$D:$D,Dashboard!$B7) -> 2300 | ... N7: =SUMIFS(Input!$F:$F,Input!$C:$C,Dashboard!N$4,Input!$D:$D,Dashboard!$B7) -> 0 | P7: =SUM(C7:N7) -> 12330
B8: Side Hustle | C8: =SUMIFS(Input!$F:$F,Input!$C:$C,Dashboard!C$4,Input!$D:$D,Dashboard!$B8) -> 199 | D8: =SUMIFS(Input!$F:$F,Input!$C:$C,Dashboard!D$4,Input!$D:$D,Dashboard!$B8) -> 228 | E8: =SUMIFS(Input!$F:$F,Input!$C:$C,Dashboard!E$4,Input!$D:$D,Dashboard!$B8) -> 59 | F8: =SUMIFS(Input!$F:$F,Input!$C:$C,Dashboard!F$4,Input!$D:$D,Dashboard!$B8) -> 258 | G8: =SUMIFS(Input!$F:$F,Input!$C:$C,Dashboard!G$4,Input!$D:$D,Dashboard!$B8) -> 1366 | H8: =SUMIFS(Input!$F:$F,Input!$C:$C,Dashboard!H$4,Input!$D:$D,Dashboard!$B8) -> 199 | I8: =SUMIFS(Input!$F:$F,Input!$C:$C,Dashboard!I$4,Input!$D:$D,Dashboard!$B8) -> 59 | J8: =SUMIFS(Input!$F:$F,Input!$C:$C,Dashboard!J$4,Input!$D:$D,Dashboard!$B8) -> 25 | ... N8: =SUMIFS(Input!$F:$F,Input!$C:$C,Dashboard!N$4,Input!$D:$D,Dashboard!$B8) -> 0 | P8: =SUM(C8:N8) -> 2393
B9: Investments | C9: =SUMIFS(Input!$F:$F,Input!$C:$C,Dashboard!C$4,Input!$D:$D,Dashboard!$B9) -> 0 | D9: =SUMIFS(Input!$F:$F,Input!$C:$C,Dashboard!D$4,Input!$D:$D,Dashboard!$B9) -> 195 | E9: =SUMIFS(Input!$F:$F,Input!$C:$C,Dashboard!E$4,Input!$D:$D,Dashboard!$B9) -> 299 | F9: =SUMIFS(Input!$F:$F,Input!$C:$C,Dashboard!F$4,Input!$D:$D,Dashboard!$B9) -> 359 | G9: =SUMIFS(Input!$F:$F,Input!$C:$C,Dashboard!G$4,Input!$D:$D,Dashboard!$B9) -> 0 | H9: =SUMIFS(Input!$F:$F,Input!$C:$C,Dashboard!H$4,Input!$D:$D,Dashboard!$B9) -> 250 | I9: =SUMIFS(Input!$F:$F,Input!$C:$C,Dashboard!I$4,Input!$D:$D,Dashboard!$B9) -> 215 | J9: =SUMIFS(Input!$F:$F,Input!$C:$C,Dashboard!J$4,Input!$D:$D,Dashboard!$B9) -> 350 | ... N9: =SUMIFS(Input!$F:$F,Input!$C:$C,Dashboard!N$4,Input!$D:$D,Dashboard!$B9) -> 0 | P9: =SUM(C9:N9) -> 1668
B10: Total Income | C10: =SUM(C6:C9) -> 4549 | D10: =SUM(D6:D9) -> 4948 | E10: =SUM(E6:E9) -> 4857 | F10: =SUM(F6:F9) -> 5360 | G10: =SUM(G6:G9) -> 6316 | H10: =SUM(H6:H9) -> 6181 | I10: =SUM(I6:I9) -> 6005 | J10: =SUM(J6:J9) -> 6175 | ... N10: =SUM(N6:N9) -> 0 | P10: =SUM(C10:N10) -> 44391
B11: MoM% growth | D11: =IF(D10=0,"",D10/C10-1) -> 0.087711585 | E11: =IF(E10=0,"",E10/D10-1) -> -0.018391269 | F11: =IF(F10=0,"",F10/E10-1) -> 0.10356187 | G11: =IF(G10=0,"",G10/F10-1) -> 0.17835821 | H11: =IF(H10=0,"",H10/G10-1) -> -0.021374288 | I11: =IF(I10=0,"",I10/H10-1) -> -0.028474357 | J11: =IF(J10=0,"",J10/I10-1) -> 0.028309742 | K11: =IF(K10=0,"",K10/J10-1) | ... N11: =IF(N10=0,"",N10/M10-1)
B13: Expenses:
B14: Rent | C14: =SUMIFS(Input!$F:$F,Input!$C:$C,Dashboard!C$4,Input!$D:$D,Dashboard!$B14) -> 1250 | D14: =SUMIFS(Input!$F:$F,Input!$C:$C,Dashboard!D$4,Input!$D:$D,Dashboard!$B14) -> 1250 | E14: =SUMIFS(Input!$F:$F,Input!$C:$C,Dashboard!E$4,Input!$D:$D,Dashboard!$B14) -> 1250 | F14: =SUMIFS(Input!$F:$F,Input!$C:$C,Dashboard!F$4,Input!$D:$D,Dashboard!$B14) -> 1250 | G14: =SUMIFS(Input!$F:$F,Input!$C:$C,Dashboard!G$4,Input!$D:$D,Dashboard!$B14) -> 1250 | H14: =SUMIFS(Input!$F:$F,Input!$C:$C,Dashboard!H$4,Input!$D:$D,Dashboard!$B14) -> 1250 | I14: =SUMIFS(Input!$F:$F,Input!$C:$C,Dashboard!I$4,Input!$D:$D,Dashboard!$B14) -> 1250 | J14: =SUMIFS(Input!$F:$F,Input!$C:$C,Dashboard!J$4,Input!$D:$D,Dashboard!$B14) -> 1250 | ... N14: =SUMIFS(Input!$F:$F,Input!$C:$C,Dashboard!N$4,Input!$D:$D,Dashboard!$B14) -> 0 | P14: =SUM(C14:N14) -> 10000
B15: Utilities | C15: =SUMIFS(Input!$F:$F,Input!$C:$C,Dashboard!C$4,Input!$D:$D,Dashboard!$B15) -> 140 | D15: =SUMIFS(Input!$F:$F,Input!$C:$C,Dashboard!D$4,Input!$D:$D,Dashboard!$B15) -> 105 | E15: =SUMIFS(Input!$F:$F,Input!$C:$C,Dashboard!E$4,Input!$D:$D,Dashboard!$B15) -> 110 | F15: =SUMIFS(Input!$F:$F,Input!$C:$C,Dashboard!F$4,Input!$D:$D,Dashboard!$B15) -> 140 | G15: =SUMIFS(Input!$F:$F,Input!$C:$C,Dashboard!G$4,Input!$D:$D,Dashboard!$B15) -> 152 | H15: =SUMIFS(Input!$F:$F,Input!$C:$C,Dashboard!H$4,Input!$D:$D,Dashboard!$B15) -> 152 | I15: =SUMIFS(Input!$F:$F,Input!$C:$C,Dashboard!I$4,Input!$D:$D,Dashboard!$B15) -> 110 | J15: =SUMIFS(Input!$F:$F,Input!$C:$C,Dashboard!J$4,Input!$D:$D,Dashboard!$B15) -> 110 | ... N15: =SUMIFS(Input!$F:$F,Input!$C:$C,Dashboard!N$4,Input!$D:$D,Dashboard!$B15) -> 0 | P15: =SUM(C15:N15) -> 1019
B16: Transport | C16: =SUMIFS(Input!$F:$F,Input!$C:$C,Dashboard!C$4,Input!$D:$D,Dashboard!$B16) -> 52 | D16: =SUMIFS(Input!$F:$F,Input!$C:$C,Dashboard!D$4,Input!$D:$D,Dashboard!$B16) -> 52 | E16: =SUMIFS(Input!$F:$F,Input!$C:$C,Dashboard!E$4,Input!$D:$D,Dashboard!$B16) -> 52 | F16: =SUMIFS(Input!$F:$F,Input!$C:$C,Dashboard!F$4,Input!$D:$D,Dashboard!$B16) -> 52 | G16: =SUMIFS(Input!$F:$F,Input!$C:$C,Dashboard!G$4,Input!$D:$D,Dashboard!$B16) -> 52 | H16: =SUMIFS(Input!$F:$F,Input!$C:$C,Dashboard!H$4,Input!$D:$D,Dashboard!$B16) -> 52 | I16: =SUMIFS(Input!$F:$F,Input!$C:$C,Dashboard!I$4,Input!$D:$D,Dashboard!$B16) -> 45 | J16: =SUMIFS(Input!$F:$F,Input!$C:$C,Dashboard!J$4,Input!$D:$D,Dashboard!$B16) -> 52 | ... N16: =SUMIFS(Input!$F:$F,Input!$C:$C,Dashboard!N$4,Input!$D:$D,Dashboard!$B16) -> 0 | P16: =SUM(C16:N16) -> 409
B17: Groceries | C17: =SUMIFS(Input!$F:$F,Input!$C:$C,Dashboard!C$4,Input!$D:$D,Dashboard!$B17) -> 449 | D17: =SUMIFS(Input!$F:$F,Input!$C:$C,Dashboard!D$4,Input!$D:$D,Dashboard!$B17) -> 305 | E17: =SUMIFS(Input!$F:$F,Input!$C:$C,Dashboard!E$4,Input!$D:$D,Dashboard!$B17) -> 208 | F17: =SUMIFS(Input!$F:$F,Input!$C:$C,Dashboard!F$4,Input!$D:$D,Dashboard!$B17) -> 449 | G17: =SUMIFS(Input!$F:$F,Input!$C:$C,Dashboard!G$4,Input!$D:$D,Dashboard!$B17) -> 449 | H17: =SUMIFS(Input!$F:$F,Input!$C:$C,Dashboard!H$4,Input!$D:$D,Dashboard!$B17) -> 560 | I17: =SUMIFS(Input!$F:$F,Input!$C:$C,Dashboard!I$4,Input!$D:$D,Dashboard!$B17) -> 208 | J17: =SUMIFS(Input!$F:$F,Input!$C:$C,Dashboard!J$4,Input!$D:$D,Dashboard!$B17) -> 208 | ... N17: =SUMIFS(Input!$F:$F,Input!$C:$C,Dashboard!N$4,Input!$D:$D,Dashboard!$B17) -> 0 | P17: =SUM(C17:N17) -> 2836
B18: Leisure | C18: =SUMIFS(Input!$F:$F,Input!$C:$C,Dashboard!C$4,Input!$D:$D,Dashboard!$B18) -> 562 | D18: =SUMIFS(Input!$F:$F,Input!$C:$C,Dashboard!D$4,Input!$D:$D,Dashboard!$B18) -> 194 | E18: =SUMIFS(Input!$F:$F,Input!$C:$C,Dashboard!E$4,Input!$D:$D,Dashboard!$B18) -> 405 | F18: =SUMIFS(Input!$F:$F,Input!$C:$C,Dashboard!F$4,Input!$D:$D,Dashboard!$B18) -> 462 | G18: =SUMIFS(Input!$F:$F,Input!$C:$C,Dashboard!G$4,Input!$D:$D,Dashboard!$B18) -> 646 | H18: =SUMIFS(Input!$F:$F,Input!$C:$C,Dashboard!H$4,Input!$D:$D,Dashboard!$B18) -> 629 | I18: =SUMIFS(Input!$F:$F,Input!$C:$C,Dashboard!I$4,Input!$D:$D,Dashboard!$B18) -> 294 | J18: =SUMIFS(Input!$F:$F,Input!$C:$C,Dashboard!J$4,Input!$D:$D,Dashboard!$B18) -> 147 | ... N18: =SUMIFS(Input!$F:$F,Input!$C:$C,Dashboard!N$4,Input!$D:$D,Dashboard!$B18) -> 0 | P18: =SUM(C18:N18) -> 3339
B19: Other | C19: =SUMIFS(Input!$F:$F,Input!$C:$C,Dashboard!C$4,Input!$D:$D,Dashboard!$B19) -> 249 | D19: =SUMIFS(Input!$F:$F,Input!$C:$C,Dashboard!D$4,Input!$D:$D,Dashboard!$B19) -> 18 | E19: =SUMIFS(Input!$F:$F,Input!$C:$C,Dashboard!E$4,Input!$D:$D,Dashboard!$B19) -> 199 | F19: =SUMIFS(Input!$F:$F,Input!$C:$C,Dashboard!F$4,Input!$D:$D,Dashboard!$B19) -> 249 | G19: =SUMIFS(Input!$F:$F,Input!$C:$C,Dashboard!G$4,Input!$D:$D,Dashboard!$B19) -> 249 | H19: =SUMIFS(Input!$F:$F,Input!$C:$C,Dashboard!H$4,Input!$D:$D,Dashboard!$B19) -> 0 | I19: =SUMIFS(Input!$F:$F,Input!$C:$C,Dashboard!I$4,Input!$D:$D,Dashboard!$B19) -> 399 | J19: =SUMIFS(Input!$F:$F,Input!$C:$C,Dashboard!J$4,Input!$D:$D,Dashboard!$B19) -> 149 | ... N19: =SUMIFS(Input!$F:$F,Input!$C:$C,Dashboard!N$4,Input!$D:$D,Dashboard!$B19) -> 0 | P19: =SUM(C19:N19) -> 1512
P20: =SUM(C20:N20) -> 0
B21: Total Expenses | C21: =SUM(C14:C20) -> 2702 | D21: =SUM(D14:D20) -> 1924 | E21: =SUM(E14:E20) -> 2224 | F21: =SUM(F14:F20) -> 2602 | G21: =SUM(G14:G20) -> 2798 | H21: =SUM(H14:H20) -> 2643 | I21: =SUM(I14:I20) -> 2306 | J21: =SUM(J14:J20) -> 1916 | ... N21: =SUM(N14:N20) -> 0 | P21: =SUM(C21:N21) -> 19115
B22: MoM% growth | D22: =IF(D21=0,"",D21/C21-1) -> -0.28793486 | E22: =IF(E21=0,"",E21/D21-1) -> 0.15592516 | F22: =IF(F21=0,"",F21/E21-1) -> 0.16996403 | G22: =IF(G21=0,"",G21/F21-1) -> 0.075326672 | H22: =IF(H21=0,"",H21/G21-1) -> -0.055396712 | I22: =IF(I21=0,"",I21/H21-1) -> -0.12750662 | J22: =IF(J21=0,"",J21/I21-1) -> -0.16912402 | K22: =IF(K21=0,"",K21/J21-1) | ... N22: =IF(N21=0,"",N21/M21-1)
B24: Savings | C24: =C10-C21 -> 1847 | D24: =D10-D21 -> 3024 | E24: =E10-E21 -> 2633 | F24: =F10-F21 -> 2758 | G24: =G10-G21 -> 3518 | H24: =H10-H21 -> 3538 | I24: =I10-I21 -> 3699 | J24: =J10-J21 -> 4259 | ... N24: =N10-N21 -> 0 | P24: =SUM(C24:N24) -> 25276
B25: MoM% growth | D25: =IF(D24=0,"",D24/C24-1) -> 0.63724959 | E25: =IF(E24=0,"",E24/D24-1) -> -0.12929894 | F25: =IF(F24=0,"",F24/E24-1) -> 0.047474364 | G25: =IF(G24=0,"",G24/F24-1) -> 0.275562 | H25: =IF(H24=0,"",H24/G24-1) -> 0.0056850483 | I25: =IF(I24=0,"",I24/H24-1) -> 0.045505936 | J25: =IF(J24=0,"",J24/I24-1) -> 0.15139227 | K25: =IF(K24=0,"",K24/J24-1) | ... N25: =IF(N24=0,"",N24/M24-1)
B28: INCOME BREAKDOWN | H28: EXPENSES BREAKDOWN

Sheet Input
B2: Actual Income And Expenses
B4: Date | C4: Month | D4: Category | E4: Description | F4: Amount | H4: Categories
B5: 44562 | C5: =TEXT(B5,"MMMM") -> January | D5: Rent | E5: Apartment split with friend | F5: 1250 | H5: Base Salary
B6: 44562 | C6: =TEXT(B6,"MMMM") -> January | D6: Utilities | E6: Higher month than usual | F6: 140 | H6: Bonus
B7: 44562 | C7: =TEXT(B7,"MMMM") -> January | D7: Transport | E7: Metro card | F7: 52 | H7: Side Hustle
B8: 44569 | C8: =TEXT(B8,"MMMM") -> January | D8: Groceries | E8: Walmart shopping | F8: 449 | H8: Investments
B9: 44572 | C9: =TEXT(B9,"MMMM") -> January | D9: Leisure | E9: Hotel in NYC | F9: 245 | H9: Rent
B10: 44573 | C10: =TEXT(B10,"MMMM") -> January | D10: Leisure | E10: Dinner with friends (invited my partner) | F10: 168 | H10: Utilities
B11: 44573 | C11: =TEXT(B11,"MMMM") -> January | D11: Leisure | E11: Drake concert | F11: 149 | H11: Transport
B12: 44575 | C12: =TEXT(B12,"MMMM") -> January | D12: Other | E12: Bought new clothes | F12: 249 | H12: Groceries
B13: 44592 | C13: =TEXT(B13,"MMMM") -> January | D13: Bonus | E13: Commissions from each sale | F13: 850 | H13: Leisure
B14: 44592 | C14: =TEXT(B14,"MMMM") -> January | D14: Base Salary | E14: 9-5 job | F14: 3500 | H14: Other
B15: 44592 | C15: =TEXT(B15,"MMMM") -> January | D15: Side Hustle | E15: Startup idea $ | F15: 199
B16: 44593 | C16: =TEXT(B16,"MMMM") -> February | D16: Rent | E16: Apartment split with friend | F16: 1250
B17: 44593 | C17: =TEXT(B17,"MMMM") -> February | D17: Utilities | E17: Average month | F17: 105
B18: 44593 | C18: =TEXT(B18,"MMMM") -> February | D18: Transport | E18: Metro card | F18: 52
B19: 44600 | C19: =TEXT(B19,"MMMM") -> February | D19: Groceries | E19: Walmart shopping | F19: 305
B20: 44603 | C20: =TEXT(B20,"MMMM") -> February | D20: Leisure | E20: Drinks out | F20: 28
B21: 44604 | C21: =TEXT(B21,"MMMM") -> February | D21: Leisure | E21: Date night | F21: 99
B22: 44604 | C22: =TEXT(B22,"MMMM") -> February | D22: Leisure | E22: Tennis x2 | F22: 67
B23: 44606 | C23: =TEXT(B23,"MMMM") -> February | D23: Other | E23: Snacks | F23: 18
B24: 44620 | C24: =TEXT(B24,"MMMM") -> February | D24: Bonus | E24: Commissions from each sale | F24: 1025
B25: 44620 | C25: =TEXT(B25,"MMMM") -> February | D25: Base Salary | E25: 9-5 job | F25: 3500
B26: 44620 | C26: =TEXT(B26,"MMMM") -> February | D26: Side Hustle | E26: Startup idea $ | F26: 228
... B57: 44693 | C57: =TEXT(B57,"MMMM") -> May | D57: Leisure | E57: Dinner with friends (invited my partner) | F57: 168
B58: 44693 | C58: =TEXT(B55,"MMMM") -> May | D58: Leisure | E58: NBA game | F58: 233
B59: 44695 | C59: =TEXT(B59,"MMMM") -> May | D59: Other | E59: Bought new clothes | F59: 249
B60: 44709 | C60: =TEXT(B60,"MMMM") -> May | D60: Bonus | E60: Commissions from each sale | F60: 1450
B61: 44709 | C61: =TEXT(B61,"MMMM") -> May | D61: Base Salary | E61: 9-5 job | F61: 3500
B62: 44709 | C62: =TEXT(B62,"MMMM") -> May | D62: Side Hustle | E62: Startup idea $ | F62: 366
B63: 44710 | C63: =TEXT(B63,"MMMM") -> May | D63: Side Hustle | E63: Lemonade | F63: 1000
B64: 44713 | C64: =TEXT(B64,"MMMM") -> June | D64: Rent | E64: Apartment split with friend | F64: 1250
B65: 44713 | C65: =TEXT(B65,"MMMM") -> June | D65: Utilities | E65: Higher month than usual | F65: 152
B66: 44713 | C66: =TEXT(B66,"MMMM") -> June | D66: Transport | E66: Metro card | F66: 52
B67: 44720 | C67: =TEXT(B67,"MMMM") -> June | D67: Groceries | E67: Walmart shopping | F67: 560
B68: 44723 | C68: =TEXT(B68,"MMMM") -> June | D68: Leisure | E68: Hotel in Dallas | F68: 280
B69: 44724 | C69: =TEXT(B69,"MMMM") -> June | D69: Leisure | E69: Dinner with friends (invited my partner) | F69: 250
B70: 44724 | C70: =TEXT(B70,"MMMM") -> June | D70: Leisure | E70: Music concert | F70: 99
... B95: 44801 | C95: =TEXT(B95,"MMMM") -> August | D95: Side Hustle | E95: Startup idea $ | F95: 25
